parsing_resumes/Employee.py
parsing_resumes/Employee2.py
parsing_resumes/EmployeeClearance.py
parsing_resumes/EmployeeEducation.py
parsing_resumes/EmployeeSkills.py
parsing_resumes/EmployeeWorkHistory.py
parsing_resumes/clean_dates.py
parsing_resumes/clean_fields.py
parsing_resumes/clearance_update.py
parsing_resumes/final_clearance.py
parsing_resumes/main.py
parsing_resumes/main2.py
parsing_resumes/main3.py
parsing_resumes/presigned.py
parsing_resumes/resume500.py
parsing_resumes/test_main.py
parsing_resumes/test_skills.py
parsingresumes-0.0.1.dist-info/METADATA
parsingresumes-0.0.1.dist-info/WHEEL
parsingresumes-0.0.1.dist-info/top_level.txt
parsingresumes-0.0.1.dist-info/RECORD
