Metadata-Version: 2.1
Name: parsingresumes
Version: 0.0.1
Summary: A package to wrap all the parsing of Sovern resume JSONs
Home-page: UNKNOWN
Author: Mansi Shah
Author-email: mshah@choosefreedomit.com
License: UNKNOWN
Platform: UNKNOWN
Classifier: Programming Language :: Python :: 3
Classifier: License :: OSI Approved :: MIT License
Classifier: Operating System :: OS Independent
Requires-Python: >=3.9
